{"cameraMode":{"drawMode":0,"name":"Shaded","section":"Shading Mode"},"sceneLighting":true,"audioPlay":false,"sceneViewState":{"m_AlwaysRefresh":false,"showFog":true,"showSkybox":true,"showFlares":true,"showImageEffects":true,"showParticleSystems":true,"showVisualEffectGraphs":true,"m_FxEnabled":true},"in2DMode":false,"pivot":{"x":-0.09125232696533203,"y":-25.224960327148439,"z":-27.19548797607422},"rotation":{"x":-0.01105886697769165,"y":0.9698700308799744,"z":-0.23920448124408723,"w":-0.04483909159898758},"size":70.70999908447266,"orthographic":false}